LICENSE
MANIFEST.in
README.rst
setup.cfg
setup.py
django_query_builder_pebble.egg-info/PKG-INFO
django_query_builder_pebble.egg-info/SOURCES.txt
django_query_builder_pebble.egg-info/dependency_links.txt
django_query_builder_pebble.egg-info/requires.txt
django_query_builder_pebble.egg-info/top_level.txt
querybuilder/__init__.py
querybuilder/apps.py
querybuilder/fields.py
querybuilder/groups.py
querybuilder/helpers.py
querybuilder/logger.py
querybuilder/query.py
querybuilder/tables.py
querybuilder/version.py
querybuilder/tests/__init__.py
querybuilder/tests/aggregate_tests.py
querybuilder/tests/date_tests.py
querybuilder/tests/field_tests.py
querybuilder/tests/group_tests.py
querybuilder/tests/helper_tests.py
querybuilder/tests/insert_tests.py
querybuilder/tests/join_tests.py
querybuilder/tests/json_tests.py
querybuilder/tests/limit_tests.py
querybuilder/tests/logger_tests.py
querybuilder/tests/models.py
querybuilder/tests/order_tests.py
querybuilder/tests/query_tests.py
querybuilder/tests/select_tests.py
querybuilder/tests/table_tests.py
querybuilder/tests/update_tests.py
querybuilder/tests/where_tests.py
querybuilder/tests/window_tests.py
querybuilder/tests/migrations/0001_initial.py
querybuilder/tests/migrations/__init__.py