Metadata-Version: 1.1
Name: django-query-builder-pebble
Version: 0.9.0
Summary: Build complex nested queries
Home-page: https://github.com/ambitioninc/django-query-builder
Author: Wes Okes
Author-email: wes.okes@gmail.com
License: MIT
Keywords: django,database,query
Platform: UNKNOWN
Classifier: Programming Language :: Python
Classifier: Programming Language :: Python :: 2.7
Classifier: Programming Language :: Python :: 3.4
Classifier: Intended Audience :: Developers
Classifier: License :: OSI Approved :: MIT License
Classifier: Operating System :: OS Independent
Classifier: Framework :: Django
Classifier: Framework :: Django :: 1.6
Classifier: Framework :: Django :: 1.7
Classifier: Development Status :: 5 - Production/Stable
